Beetle_S3Uploader-0.1.0.dist-info/WHEEL
Beetle_S3Uploader-0.1.0.dist-info/DESCRIPTION.rst
Beetle_S3Uploader-0.1.0.dist-info/RECORD
Beetle_S3Uploader-0.1.0.dist-info/METADATA
Beetle_S3Uploader-0.1.0.dist-info/metadata.json
Beetle_S3Uploader-0.1.0.dist-info/top_level.txt
beetle_s3uploader/__init__.py
