Metadata-Version: 2.0
Name: Beetle-S3Uploader
Version: 0.1.0
Summary: Beetle plugin to upload the site to S3
Home-page: https://github.com/cknv/beetle-s3uploader
Author: Esben Sonne
Author-email: esbensonne+code@gmail.com
License: MIT
Platform: UNKNOWN
Classifier: Environment :: Plugins
Classifier: Environment :: Console
Classifier: Development Status :: 3 - Alpha
Classifier: Intended Audience :: Developers
Classifier: License :: OSI Approved :: MIT License
Classifier: Programming Language :: Python :: 3
Classifier: Topic :: Internet :: WWW/HTTP :: Site Management
Requires-Dist: boto
